{
    "lines":[
        {"mode":"lesson","words":[{"w":"Conversation"}]},
        {"mode":"qa","lineno":0, "lines":[
            {"words":[{"w":"حَامِدٌ","e":""},{"w":":","sp":[0]},{"w":"مَنْ","e":"who"},{"w":"أَنْتَ؟","e":"you"}]},
            {"words":[{"w":"مُحَمَّدٌ","e":""},{"w":":","sp":[0]},{"w":"أَنَا","e":"i"},{"w":"طَالِبٌ","e":"student"},{"w":"بِالْجَامِعَةِ.","e":"university","sp":[0,2]}]},
            {"words":[{"w":"حَامِدٌ","e":""},{"w":":","sp":[0]},{"w":"أَأَنْتَ","e":"you","sp":[0,2]},{"w":"طَالِبٌ","e":"student"},{"w":"جَدِيدٌ؟","e":"new"}]},
            {"words":[{"w":"مُحَمَّدٌ","e":""},{"w":":","sp":[0]},{"w":"نَعَمْ،","e":"yes"},{"w":"أَنَا","e":"i"},{"w":"طَالِبٌ","e":""},{"w":"جَدِيدٌ.","e":""}]},
            {"words":[{"w":"حَامِدٌ","e":""},{"w":":","sp":[0]},{"w":"مِنْ","e":"from"},{"w":"أَيْنَ","e":"where"},{"w":"أَنْتَ؟","e":"you"}]},
            {"words":[{"w":"مُحَمَّدٌ","e":""},{"w":":","sp":[0]},{"w":"أَنَا","e":"i"},{"w":"مِنَ","e":"from"},{"w":"الْهِنْدِ.","e":"India"}]},
            {"words":[{"w":"حَامِدٌ","e":""},{"w":":","sp":[0]},{"w":"مَا","e":"what"},{"w":"اسْمُكَ؟","e":"name","sp":[5,7]}]},
            {"words":[{"w":"مُحَمَّدٌ","e":""},{"w":":","sp":[0]},{"w":"اِسْمِي","e":"name","sp":[6]},{"w":"مُحَمَّدٌ.","e":"Muhammad"}]},
            {"words":[{"w":"حَامِدٌ","e":""},{"w":":","sp":[0]},{"w":"وَمَنْ","e":"who","sp":[0,2]},{"w":"هَدْا","e":"this"},{"w":"الْفَتَي","e":"young man"},{"w":"الَّذِي","e":"who","sp":[0]},{"w":"مَعَكَ؟","e":"with","sp":[4,6]}]},
            {"words":[{"w":"مُحَمَّدٌ","e":""},{"w":":","sp":[0]},{"w":"هُوَ","e":"he"},{"w":"زَمِيلِي.","e":"classmate","sp":[7,8]}]},
            {"words":[{"w":"حَامِدٌ","e":""},{"w":":","sp":[0]},{"w":"أَهُوَ","e":"he","sp":[0,2]},{"w":"أَيْصًا","e":"also"},{"w":"مِنَ","e":"from"},{"w":"الْهِنْدِ؟","e":"India"}]},
            {"words":[{"w":"مُحَمَّدٌ","e":""},{"w":":","sp":[0]},{"w":"لاَ،","e":"no"},{"w":"هُوَ","e":"he"},{"w":"مِنَ","e":"from"},{"w":"اليَابَانِ.","e":"Japan"}]},
            {"words":[{"w":"حَامِدٌ","e":""},{"w":":","sp":[0]},{"w":"مَا","e":"what"},{"w":"اسْمُهُ؟","e":"name","sp":[5,7]}]},
            {"words":[{"w":"مُحَمَّدٌ","e":""},{"w":":","sp":[0]},{"w":"اِسْمُهُ","e":"name","sp":[6]},{"w":"حَمْزَةُ.","e":""}]},
            {"words":[{"w":"حَامِدٌ","e":""},{"w":":","sp":[0]},{"w":"مَا","e":"what"},{"w":"لُغَتُكَ","e":"language","sp":[6]},{"w":"يَا","e":"oh"},{"w":"مُحَمَّدٌ؟","e":""}]},
            {"words":[{"w":"مُحَمَّدٌ","e":""},{"w":":","sp":[0]},{"w":"لُغَتِي","e":"language","sp":[6]},{"w":"الأُرْدِيَّةُ.","e":"Urdu"}]}
        ]}
    ]
}